{
  "cohortProgression": {
    "13": [
      {
        "cohort": "70-74 (2025)",
        "expected": "0.275",
        "actual": 0.21,
        "survivalRate": 0.9467709347753169,
        "actualRatio": "0.724",
        "expectedRatio": "0.947"
      },
      {
        "cohort": "75-79 (2025)",
        "expected": "0.233",
        "actual": 0.19,
        "survivalRate": 0.8958330590435345,
        "actualRatio": "0.731",
        "expectedRatio": "0.896"
      },
      {
        "cohort": "80-84 (2025)",
        "expected": "0.081",
        "actual": 0.06,
        "survivalRate": 0.8109022310130007,
        "actualRatio": "0.600",
        "expectedRatio": "0.811"
      },
      {
        "cohort": "85-89 (2025)",
        "expected": "0.040",
        "actual": 0.03,
        "survivalRate": 0.6741908111168233,
        "actualRatio": "0.500",
        "expectedRatio": "0.674"
      },
      {
        "cohort": "90-94 (2025)",
        "expected": "0.015",
        "actual": 0.01,
        "survivalRate": 0.48455615049627776,
        "actualRatio": "0.333",
        "expectedRatio": "0.485"
      },
      {
        "cohort": "75-79 (2030)",
        "expected": "0.188",
        "actual": 0.16,
        "survivalRate": 0.8958330590435345,
        "actualRatio": "0.762",
        "expectedRatio": "0.896"
      },
      {
        "cohort": "85-89 (2030)",
        "expected": "0.040",
        "actual": 0.03,
        "survivalRate": 0.6741908111168233,
        "actualRatio": "0.500",
        "expectedRatio": "0.674"
      },
      {
        "cohort": "90-94 (2030)",
        "expected": "0.015",
        "actual": 0.01,
        "survivalRate": 0.48455615049627776,
        "actualRatio": "0.333",
        "expectedRatio": "0.485"
      },
      {
        "cohort": "75-79 (2035)",
        "expected": "0.206",
        "actual": 0.18,
        "survivalRate": 0.8958330590435345,
        "actualRatio": "0.783",
        "expectedRatio": "0.896"
      },
      {
        "cohort": "80-84 (2035)",
        "expected": "0.130",
        "actual": 0.09,
        "survivalRate": 0.8109022310130007,
        "actualRatio": "0.563",
        "expectedRatio": "0.811"
      },
      {
        "cohort": "85-89 (2035)",
        "expected": "0.094",
        "actual": 0.05,
        "survivalRate": 0.6741908111168233,
        "actualRatio": "0.357",
        "expectedRatio": "0.674"
      },
      {
        "cohort": "90-94 (2035)",
        "expected": "0.015",
        "actual": 0.01,
        "survivalRate": 0.48455615049627776,
        "actualRatio": "0.333",
        "expectedRatio": "0.485"
      },
      {
        "cohort": "75-79 (2040)",
        "expected": "0.296",
        "actual": 0.23,
        "survivalRate": 0.8958330590435345,
        "actualRatio": "0.697",
        "expectedRatio": "0.896"
      },
      {
        "cohort": "80-84 (2040)",
        "expected": "0.146",
        "actual": 0.12,
        "survivalRate": 0.8109022310130007,
        "actualRatio": "0.667",
        "expectedRatio": "0.811"
      },
      {
        "cohort": "85-89 (2040)",
        "expected": "0.061",
        "actual": 0.04,
        "survivalRate": 0.6741908111168233,
        "actualRatio": "0.444",
        "expectedRatio": "0.674"
      },
      {
        "cohort": "70-74 (2045)",
        "expected": "0.180",
        "actual": 0.13,
        "survivalRate": 0.9467709347753169,
        "actualRatio": "0.684",
        "expectedRatio": "0.947"
      },
      {
        "cohort": "80-84 (2045)",
        "expected": "0.187",
        "actual": 0.15,
        "survivalRate": 0.8109022310130007,
        "actualRatio": "0.652",
        "expectedRatio": "0.811"
      },
      {
        "cohort": "85-89 (2045)",
        "expected": "0.081",
        "actual": 0.05,
        "survivalRate": 0.6741908111168233,
        "actualRatio": "0.417",
        "expectedRatio": "0.674"
      },
      {
        "cohort": "90-94 (2045)",
        "expected": "0.019",
        "actual": 0.01,
        "survivalRate": 0.48455615049627776,
        "actualRatio": "0.250",
        "expectedRatio": "0.485"
      }
    ],
    "01": [
      {
        "cohort": "75-79 (2025)",
        "expected": "0.174",
        "actual": 0.14,
        "survivalRate": 0.8691956799091438,
        "actualRatio": "0.700",
        "expectedRatio": "0.869"
      },
      {
        "cohort": "80-84 (2025)",
        "expected": "0.061",
        "actual": 0.04,
        "survivalRate": 0.7650080385012706,
        "actualRatio": "0.500",
        "expectedRatio": "0.765"
      },
      {
        "cohort": "85-89 (2025)",
        "expected": "0.030",
        "actual": 0.02,
        "survivalRate": 0.6026080187329591,
        "actualRatio": "0.400",
        "expectedRatio": "0.603"
      },
      {
        "cohort": "90-94 (2025)",
        "expected": "0.008",
        "actual": 0,
        "survivalRate": 0.3906025978446486,
        "actualRatio": "0.000",
        "expectedRatio": "0.391"
      },
      {
        "cohort": "70-74 (2030)",
        "expected": "0.187",
        "actual": 0.16,
        "survivalRate": 0.9327647937814779,
        "actualRatio": "0.800",
        "expectedRatio": "0.933"
      },
      {
        "cohort": "75-79 (2030)",
        "expected": "0.183",
        "actual": 0.14,
        "survivalRate": 0.8691956799091438,
        "actualRatio": "0.667",
        "expectedRatio": "0.869"
      },
      {
        "cohort": "80-84 (2030)",
        "expected": "0.107",
        "actual": 0.08,
        "survivalRate": 0.7650080385012706,
        "actualRatio": "0.571",
        "expectedRatio": "0.765"
      },
      {
        "cohort": "85-89 (2030)",
        "expected": "0.024",
        "actual": 0.02,
        "survivalRate": 0.6026080187329591,
        "actualRatio": "0.500",
        "expectedRatio": "0.603"
      },
      {
        "cohort": "90-94 (2030)",
        "expected": "0.008",
        "actual": 0,
        "survivalRate": 0.3906025978446486,
        "actualRatio": "0.000",
        "expectedRatio": "0.391"
      },
      {
        "cohort": "70-74 (2035)",
        "expected": "0.224",
        "actual": 0.17,
        "survivalRate": 0.9327647937814779,
        "actualRatio": "0.708",
        "expectedRatio": "0.933"
      },
      {
        "cohort": "80-84 (2035)",
        "expected": "0.107",
        "actual": 0.08,
        "survivalRate": 0.7650080385012706,
        "actualRatio": "0.571",
        "expectedRatio": "0.765"
      },
      {
        "cohort": "85-89 (2035)",
        "expected": "0.048",
        "actual": 0.02,
        "survivalRate": 0.6026080187329591,
        "actualRatio": "0.250",
        "expectedRatio": "0.603"
      },
      {
        "cohort": "90-94 (2035)",
        "expected": "0.008",
        "actual": 0,
        "survivalRate": 0.3906025978446486,
        "actualRatio": "0.000",
        "expectedRatio": "0.391"
      },
      {
        "cohort": "75-79 (2040)",
        "expected": "0.148",
        "actual": 0.1,
        "survivalRate": 0.8691956799091438,
        "actualRatio": "0.588",
        "expectedRatio": "0.869"
      },
      {
        "cohort": "80-84 (2040)",
        "expected": "0.099",
        "actual": 0.08,
        "survivalRate": 0.7650080385012706,
        "actualRatio": "0.615",
        "expectedRatio": "0.765"
      },
      {
        "cohort": "85-89 (2040)",
        "expected": "0.048",
        "actual": 0.03,
        "survivalRate": 0.6026080187329591,
        "actualRatio": "0.375",
        "expectedRatio": "0.603"
      },
      {
        "cohort": "90-94 (2040)",
        "expected": "0.008",
        "actual": 0.01,
        "survivalRate": 0.3906025978446486,
        "actualRatio": "0.500",
        "expectedRatio": "0.391"
      },
      {
        "cohort": "70-74 (2045)",
        "expected": "0.149",
        "actual": 0.13,
        "survivalRate": 0.9327647937814779,
        "actualRatio": "0.813",
        "expectedRatio": "0.933"
      },
      {
        "cohort": "80-84 (2045)",
        "expected": "0.077",
        "actual": 0.05,
        "survivalRate": 0.7650080385012706,
        "actualRatio": "0.500",
        "expectedRatio": "0.765"
      },
      {
        "cohort": "85-89 (2045)",
        "expected": "0.048",
        "actual": 0.03,
        "survivalRate": 0.6026080187329591,
        "actualRatio": "0.375",
        "expectedRatio": "0.603"
      },
      {
        "cohort": "90-94 (2045)",
        "expected": "0.012",
        "actual": 0,
        "survivalRate": 0.3906025978446486,
        "actualRatio": "0.000",
        "expectedRatio": "0.391"
      }
    ],
    "02": [
      {
        "cohort": "70-74 (2025)",
        "expected": "0.019",
        "actual": 0.01,
        "survivalRate": 0.9303459560730069,
        "actualRatio": "0.500",
        "expectedRatio": "0.930"
      },
      {
        "cohort": "75-79 (2025)",
        "expected": "0.017",
        "actual": 0.01,
        "survivalRate": 0.8646284877647391,
        "actualRatio": "0.500",
        "expectedRatio": "0.865"
      },
      {
        "cohort": "80-84 (2025)",
        "expected": "0.008",
        "actual": 0,
        "survivalRate": 0.7572430742982555,
        "actualRatio": "0.000",
        "expectedRatio": "0.757"
      },
      {
        "cohort": "70-74 (2030)",
        "expected": "0.019",
        "actual": 0.01,
        "survivalRate": 0.9303459560730069,
        "actualRatio": "0.500",
        "expectedRatio": "0.930"
      },
      {
        "cohort": "75-79 (2030)",
        "expected": "0.009",
        "actual": 0.01,
        "survivalRate": 0.8646284877647391,
        "actualRatio": "1.000",
        "expectedRatio": "0.865"
      },
      {
        "cohort": "80-84 (2030)",
        "expected": "0.008",
        "actual": 0.01,
        "survivalRate": 0.7572430742982555,
        "actualRatio": "1.000",
        "expectedRatio": "0.757"
      },
      {
        "cohort": "70-74 (2035)",
        "expected": "0.019",
        "actual": 0.01,
        "survivalRate": 0.9303459560730069,
        "actualRatio": "0.500",
        "expectedRatio": "0.930"
      },
      {
        "cohort": "75-79 (2035)",
        "expected": "0.009",
        "actual": 0.01,
        "survivalRate": 0.8646284877647391,
        "actualRatio": "1.000",
        "expectedRatio": "0.865"
      },
      {
        "cohort": "80-84 (2035)",
        "expected": "0.008",
        "actual": 0.01,
        "survivalRate": 0.7572430742982555,
        "actualRatio": "1.000",
        "expectedRatio": "0.757"
      },
      {
        "cohort": "85-89 (2035)",
        "expected": "0.006",
        "actual": 0,
        "survivalRate": 0.5908049951918067,
        "actualRatio": "0.000",
        "expectedRatio": "0.591"
      },
      {
        "cohort": "75-79 (2040)",
        "expected": "0.009",
        "actual": 0.01,
        "survivalRate": 0.8646284877647391,
        "actualRatio": "1.000",
        "expectedRatio": "0.865"
      },
      {
        "cohort": "80-84 (2040)",
        "expected": "0.008",
        "actual": 0.01,
        "survivalRate": 0.7572430742982555,
        "actualRatio": "1.000",
        "expectedRatio": "0.757"
      },
      {
        "cohort": "85-89 (2040)",
        "expected": "0.006",
        "actual": 0,
        "survivalRate": 0.5908049951918067,
        "actualRatio": "0.000",
        "expectedRatio": "0.591"
      },
      {
        "cohort": "75-79 (2045)",
        "expected": "0.009",
        "actual": 0.01,
        "survivalRate": 0.8646284877647391,
        "actualRatio": "1.000",
        "expectedRatio": "0.865"
      },
      {
        "cohort": "80-84 (2045)",
        "expected": "0.008",
        "actual": 0.01,
        "survivalRate": 0.7572430742982555,
        "actualRatio": "1.000",
        "expectedRatio": "0.757"
      },
      {
        "cohort": "85-89 (2045)",
        "expected": "0.006",
        "actual": 0,
        "survivalRate": 0.5908049951918067,
        "actualRatio": "0.000",
        "expectedRatio": "0.591"
      }
    ]
  },
  "shareRateConsistency": {
    "13": {
      "20-24": [
        {
          "year": 2025,
          "count": 0.02
        },
        {
          "year": 2030,
          "count": 0.02
        },
        {
          "year": 2035,
          "count": 0.02
        },
        {
          "year": 2040,
          "count": 0.02
        },
        {
          "year": 2045,
          "count": 0.02
        },
        {
          "year": 2050,
          "count": 0.01
        }
      ],
      "25-29": [
        {
          "year": 2025,
          "count": 0.02
        },
        {
          "year": 2030,
          "count": 0.02
        },
        {
          "year": 2035,
          "count": 0.02
        },
        {
          "year": 2040,
          "count": 0.02
        },
        {
          "year": 2045,
          "count": 0.02
        },
        {
          "year": 2050,
          "count": 0.02
        }
      ],
      "30-34": [
        {
          "year": 2025,
          "count": 0.1
        },
        {
          "year": 2030,
          "count": 0.11
        },
        {
          "year": 2035,
          "count": 0.1
        },
        {
          "year": 2040,
          "count": 0.09
        },
        {
          "year": 2045,
          "count": 0.1
        },
        {
          "year": 2050,
          "count": 0.08
        }
      ]
    },
    "01": {
      "20-24": [
        {
          "year": 2025,
          "count": 0.01
        },
        {
          "year": 2030,
          "count": 0.01
        },
        {
          "year": 2035,
          "count": 0.01
        },
        {
          "year": 2040,
          "count": 0.01
        },
        {
          "year": 2045,
          "count": 0.01
        },
        {
          "year": 2050,
          "count": 0.01
        }
      ],
      "25-29": [
        {
          "year": 2025,
          "count": 0.01
        },
        {
          "year": 2030,
          "count": 0.01
        },
        {
          "year": 2035,
          "count": 0.01
        },
        {
          "year": 2040,
          "count": 0.01
        },
        {
          "year": 2045,
          "count": 0.01
        },
        {
          "year": 2050,
          "count": 0.01
        }
      ],
      "30-34": [
        {
          "year": 2025,
          "count": 0.08
        },
        {
          "year": 2030,
          "count": 0.07
        },
        {
          "year": 2035,
          "count": 0.07
        },
        {
          "year": 2040,
          "count": 0.08
        },
        {
          "year": 2045,
          "count": 0.07
        },
        {
          "year": 2050,
          "count": 0.06
        }
      ]
    },
    "02": {
      "20-24": [
        {
          "year": 2025,
          "count": 0
        },
        {
          "year": 2030,
          "count": 0
        },
        {
          "year": 2035,
          "count": 0
        },
        {
          "year": 2040,
          "count": 0
        },
        {
          "year": 2045,
          "count": 0
        },
        {
          "year": 2050,
          "count": 0
        }
      ],
      "25-29": [
        {
          "year": 2025,
          "count": 0
        },
        {
          "year": 2030,
          "count": 0
        },
        {
          "year": 2035,
          "count": 0
        },
        {
          "year": 2040,
          "count": 0
        },
        {
          "year": 2045,
          "count": 0
        },
        {
          "year": 2050,
          "count": 0
        }
      ],
      "30-34": [
        {
          "year": 2025,
          "count": 0.01
        },
        {
          "year": 2030,
          "count": 0.01
        },
        {
          "year": 2035,
          "count": 0.01
        },
        {
          "year": 2040,
          "count": 0.01
        },
        {
          "year": 2045,
          "count": 0.01
        },
        {
          "year": 2050,
          "count": 0.01
        }
      ]
    }
  },
  "mortalityApplication": {
    "13": [
      {
        "ageGroup": "70-74",
        "survivalRate": 0.9467709347753169,
        "mortalityRate": 0.05322906522468307
      },
      {
        "ageGroup": "75-79",
        "survivalRate": 0.8958330590435345,
        "mortalityRate": 0.1041669409564655
      },
      {
        "ageGroup": "80-84",
        "survivalRate": 0.8109022310130007,
        "mortalityRate": 0.18909776898699926
      },
      {
        "ageGroup": "85-89",
        "survivalRate": 0.6741908111168233,
        "mortalityRate": 0.32580918888317667
      },
      {
        "ageGroup": "90-94",
        "survivalRate": 0.48455615049627776,
        "mortalityRate": 0.5154438495037222
      },
      {
        "ageGroup": "95-99",
        "survivalRate": 0.27547529920533975,
        "mortalityRate": 0.7245247007946602
      }
    ],
    "01": [
      {
        "ageGroup": "70-74",
        "survivalRate": 0.9327647937814779,
        "mortalityRate": 0.06723520621852208
      },
      {
        "ageGroup": "75-79",
        "survivalRate": 0.8691956799091438,
        "mortalityRate": 0.13080432009085619
      },
      {
        "ageGroup": "80-84",
        "survivalRate": 0.7650080385012706,
        "mortalityRate": 0.23499196149872936
      },
      {
        "ageGroup": "85-89",
        "survivalRate": 0.6026080187329591,
        "mortalityRate": 0.3973919812670409
      },
      {
        "ageGroup": "90-94",
        "survivalRate": 0.3906025978446486,
        "mortalityRate": 0.6093974021553514
      },
      {
        "ageGroup": "95-99",
        "survivalRate": 0.18196303239256623,
        "mortalityRate": 0.8180369676074337
      }
    ],
    "02": [
      {
        "ageGroup": "70-74",
        "survivalRate": 0.9303459560730069,
        "mortalityRate": 0.06965404392699315
      },
      {
        "ageGroup": "75-79",
        "survivalRate": 0.8646284877647391,
        "mortalityRate": 0.1353715122352609
      },
      {
        "ageGroup": "80-84",
        "survivalRate": 0.7572430742982555,
        "mortalityRate": 0.24275692570174445
      },
      {
        "ageGroup": "85-89",
        "survivalRate": 0.5908049951918067,
        "mortalityRate": 0.40919500480819326
      },
      {
        "ageGroup": "90-94",
        "survivalRate": 0.3758679160368371,
        "mortalityRate": 0.6241320839631629
      },
      {
        "ageGroup": "95-99",
        "survivalRate": 0.16868555581182745,
        "mortalityRate": 0.8313144441881726
      }
    ]
  },
  "overallQuality": {
    "13": {
      "totalMembers2025": 2.56,
      "totalMembers2030": 2.4199999999999995,
      "changePercent": -5.468750000000022
    },
    "01": {
      "totalMembers2025": 2.01,
      "totalMembers2030": 1.77,
      "changePercent": -11.940298507462677
    },
    "02": {
      "totalMembers2025": 0.17,
      "totalMembers2030": 0.15000000000000002,
      "changePercent": -11.764705882352933
    }
  }
}